devtools_iban/__init__.py
devtools_iban-1.0.1.dist-info/METADATA
devtools_iban-1.0.1.dist-info/WHEEL
devtools_iban-1.0.1.dist-info/top_level.txt
devtools_iban-1.0.1.dist-info/RECORD
