Metadata-Version: 2.1
Name: devtools-iban
Version: 1.0.1
Summary: IBAN validator
Home-page: https://devtools.at/tools/iban-validator
Author: DevTools.at
Author-email: hello@devtools.at
Project-URL: Homepage, https://devtools.at/tools/iban-validator
Project-URL: Repository, https://github.com/devtools-at/iban-validator
Classifier: Development Status :: 4 - Beta
Classifier: Intended Audience :: Developers
Classifier: License :: OSI Approved :: MIT License
Classifier: Programming Language :: Python :: 3
Requires-Python: >=3.8
